dramasub/__init__.py
dramasub/dramasub.py
dramasub/test.py
dramasub-0.0.3.dist-info/LICENSE.md
dramasub-0.0.3.dist-info/METADATA
dramasub-0.0.3.dist-info/WHEEL
dramasub-0.0.3.dist-info/entry_points.txt
dramasub-0.0.3.dist-info/top_level.txt
dramasub-0.0.3.dist-info/RECORD
