Metadata-Version: 2.1
Name: dramasub
Version: 0.0.3
Summary: script to generate accompanying visuals for voice dramas from .ass subtitle files
Author: GenericTLAccount
Project-URL: Homepage, https://github.com/GenericTLAccount/dramasub
Keywords: drama cd,voice drama,subtitle,.ass,visuals
Classifier: Development Status :: 3 - Alpha
Classifier: Programming Language :: Python :: 3
Classifier: License :: OSI Approved :: GNU General Public License v3 (GPLv3)
Classifier: Operating System :: Microsoft :: Windows :: Windows 11
Requires-Python: >=3.10
License-File: LICENSE.md
Requires-Dist: wand
